{
    "configurations": [
        {
            "name": "Win32",
            "includePath": [
                "d:/Programming/DSA/**"
            ],
            "defines": [
                "_DEBUG",
                "UNICODE",
                "_UNICODE"
            ],
            "cStandard": "c23",
            "cppStandard": "c++23",
            "intelliSenseMode": "windows-gcc-x64",
            "mergeConfigurations": false,
            "compilerPath": "C:/MinGW/bin/g++.exe",
            "browse": {
                "path": [
                    "d:/Programming/DSA/**",
                    "${workspaceFolder}"
                ],
                "limitSymbolsToIncludedHeaders": true
            }
        },
        {
            "name": "GCC",
            "includePath": [
                "${workspaceFolder}/**"
            ],
            "defines": [
                "_DEBUG",
                "UNICODE",
                "_UNICODE"
            ],
            "cStandard": "c23",
            "cppStandard": "c++23",
            "intelliSenseMode": "windows-gcc-x64",
            "compilerPath": "C:/MinGW/bin/g++.exe"
        }
    ],
    "version": 4
}